treelite/model_builder.py
treelite/path_config.py
treelite/util.py
treelite/frontend.py
treelite/__init__.py
treelite/core.py
treelite/model.py
treelite/VERSION
treelite/py.typed
treelite/libpath.py
treelite/gtil/__init__.py
treelite/gtil/gtil.py
treelite/sklearn/importer.py
treelite/sklearn/exporter.py
treelite/sklearn/__init__.py
treelite/sklearn/isolation_forest.py
treelite/lib/libtreelite.dylib
treelite-4.6.1.dist-info/RECORD
treelite-4.6.1.dist-info/WHEEL
treelite-4.6.1.dist-info/METADATA
